topsis_ritisha_102303552/__init__.py
topsis_ritisha_102303552/topsis.py
topsis_ritisha_102303552-1.0.0.dist-info/licenses/LICENSE
topsis_ritisha_102303552-1.0.0.dist-info/METADATA
topsis_ritisha_102303552-1.0.0.dist-info/WHEEL
topsis_ritisha_102303552-1.0.0.dist-info/entry_points.txt
topsis_ritisha_102303552-1.0.0.dist-info/top_level.txt
topsis_ritisha_102303552-1.0.0.dist-info/RECORD
