Metadata-Version: 2.4
Name: Topsis-Ritisha-102303552
Version: 1.0.0
Summary: TOPSIS implementation for multi-criteria decision making
Author: Ritisha Sidana
Author-email: rsidana1_be23@thapar.edu
Requires-Python: >=3.7
License-File: LICENSE
Requires-Dist: pandas
Requires-Dist: numpy
Requires-Dist: openpyxl
Dynamic: author
Dynamic: author-email
Dynamic: description
Dynamic: description-content-type
Dynamic: license-file
Dynamic: requires-dist
Dynamic: requires-python
Dynamic: summary
